pyosa/__about__.py
pyosa/__init__.py
pyosa/main.py
pyosa/tests/test_estimate.py
pyosa-0.0.1.dist-info/LICENSE
pyosa-0.0.1.dist-info/METADATA
pyosa-0.0.1.dist-info/WHEEL
pyosa-0.0.1.dist-info/top_level.txt
pyosa-0.0.1.dist-info/RECORD
