Metadata-Version: 2.1
Name: pyosa
Version: 0.0.1
Summary: Simple estimator of the irregular open surface area in 3-D
Author-email: Ante Kapetanović <akape00@gmail.com>
License: MIT License
Project-URL: Code, https://github.com/akapet00/pyosa
Keywords: point cloud,triangle mesh,surface reconstruction,surface area
Classifier: Development Status :: 4 - Beta
Classifier: Intended Audience :: Science/Research
Classifier: Operating System :: OS Independent
Classifier: Programming Language :: Python
Classifier: Programming Language :: Python :: 3
Classifier: Programming Language :: Python :: 3.7
Classifier: Programming Language :: Python :: 3.8
Classifier: Programming Language :: Python :: 3.9
Classifier: Programming Language :: Python :: 3.10
Classifier: Programming Language :: Python :: 3.11
Classifier: Topic :: Scientific/Engineering
Classifier: Topic :: Utilities
Requires-Python: >=3.7
License-File: LICENSE
Requires-Dist: numpy (>=1.20.0)
Requires-Dist: open3d (==0.16.0)
Requires-Dist: scipy
